<?xml version="1.0" encoding="gb2312"?>
<!--雷达站参数-->
<Radar>
  <Item StationNum="Z9719" StationName="十堰" RadarType="SB" x="110.744" y="32.599" z="0.0"/>
  <Item StationNum="Z9001" StationName="北京" RadarType="CC" x="116.291" y="39.945" z="0.0"/>
  <Item StationNum="Z9736" StationName="常德" RadarType="SB" x="111.707" y="29.181" z="0.0"/>
  <Item StationNum="Z9010" StationName="大兴" RadarType="SA" x="116.472" y="39.809" z="0.0"/>
  <Item StationNum="Z9746" StationName="永州" RadarType="SB" x="111.612" y="26.224" z="0.0"/>
  <Item StationNum="Z9200" StationName="广州" RadarType="SA" x="113.356" y="23.004" z="0.0"/>
  <Item StationNum="Z9220" StationName="塘沽" RadarType="SA" x="117.718" y="39.044" z="0.0"/>
  <Item StationNum="Z9230" StationName="重庆" RadarType="SA" x="106.489" y="29.523" z="0.0"/>
  <Item StationNum="Z9240" StationName="沈阳" RadarType="SC" x="123.649" y="41.923" z="0.0"/>
  <Item StationNum="Z9270" StationName="武汉" RadarType="SA" x="114.378" y="30.517" z="0.0"/>
  <Item StationNum="Z9745" StationName="怀化" RadarType="CB" x="110.003" y="27.566" z="0.0"/>
  <Item StationNum="Z9751" StationName="韶关" RadarType="SA" x="113.569" y="24.791" z="0.0"/>
  <Item StationNum="Z9280" StationName="成都" RadarType="SC" x="104.016" y="30.663" z="0.0"/>
  <Item StationNum="Z9753" StationName="梅州" RadarType="SA" x="115.975" y="24.256" z="0.0"/>
  <Item StationNum="Z9290" StationName="西安" RadarType="CB" x="108.972" y="34.443" z="0.0"/>
  <Item StationNum="Z9754" StationName="汕头" RadarType="SA" x="116.742" y="23.282" z="0.0"/>
  <Item StationNum="Z9755" StationName="深圳" RadarType="SA" x="114.006" y="22.542" z="0.0"/>
  <Item StationNum="Z9772" StationName="柳州" RadarType="SB" x="109.4" y="24.335" z="0.0"/>
  <Item StationNum="Z9773" StationName="桂林" RadarType="SB" x="110.307" y="25.322" z="0.0"/>
  <Item StationNum="Z9311" StationName="石家庄" RadarType="SA" x="114.712" y="38.352" z="0.0"/>
  <Item StationNum="Z9314" StationName="承德" RadarType="CB" x="117.919" y="40.974" z="0.0"/>
  <Item StationNum="Z9351" StationName="太原" RadarType="CC" x="112.579" y="37.735" z="0.0"/>
  <Item StationNum="Z9791" StationName="南昌" RadarType="SA" x="115.901" y="28.589" z="0.0"/>
  <Item StationNum="Z9792" StationName="九江" RadarType="SA" x="115.955" y="29.536" z="0.0"/>
  <Item StationNum="Z9796" StationName="吉安" RadarType="SC" x="114.913" y="27.042" z="0.0"/>
  <Item StationNum="Z9352" StationName="大同" RadarType="CB" x="113.39" y="40.072" z="0.0"/>
  <Item StationNum="Z9797" StationName="赣州" RadarType="SC" x="114.97" y="25.88" z="0.0"/>
  <Item StationNum="Z9357" StationName="临汾" RadarType="CC" x="111.496" y="36.061" z="0.0"/>
  <Item StationNum="Z9370" StationName="商丘" RadarType="SB" x="115.63" y="34.407" z="0.0"/>
  <Item StationNum="Z9816" StationName="绵阳" RadarType="SC" x="104.762" y="31.455" z="0.0"/>
  <Item StationNum="Z9817" StationName="南充" RadarType="SC" x="106.078" y="30.825" z="0.0"/>
  <Item StationNum="Z9371" StationName="郑州" RadarType="SA" x="113.697" y="34.704" z="0.0"/>
  <Item StationNum="Z9831" StationName="宜宾" RadarType="SC" x="104.565" y="28.817" z="0.0"/>
  <Item StationNum="Z9377" StationName="南阳" RadarType="SB" x="112.493" y="33.021" z="0.0"/>
  <Item StationNum="Z9393" StationName="濮阳" RadarType="SB" x="114.945" y="35.776" z="0.0"/>
  <Item StationNum="Z9396" StationName="驻马店" RadarType="SB" x="114.02" y="33.009" z="0.0"/>
  <Item StationNum="Z9398" StationName="三门峡" RadarType="SB" x="111.13" y="34.679" z="0.0"/>
  <Item StationNum="Z9411" StationName="大连" RadarType="SC" x="121.648" y="38.908" z="0.0"/>
  <Item StationNum="Z9417" StationName="营口" RadarType="SA" x="122.273" y="40.674" z="0.0"/>
  <Item StationNum="Z9834" StationName="西昌" RadarType="CD" x="102.411" y="27.88" z="0.0"/>
  <Item StationNum="Z9839" StationName="广元" RadarType="SC" x="105.811" y="32.397" z="0.0"/>
  <Item StationNum="Z9431" StationName="长春" RadarType="CC" x="125.247" y="43.899" z="0.0"/>
  <Item StationNum="Z9851" StationName="贵阳" RadarType="CD" x="106.726" y="26.59" z="0.0"/>
  <Item StationNum="Z9436" StationName="白城" RadarType="CC" x="122.796" y="45.615" z="0.0"/>
  <Item StationNum="Z9451" StationName="哈尔滨" RadarType="CC" x="126.728" y="45.724" z="0.0"/>
  <Item StationNum="Z9857" StationName="毕节" RadarType="CD" x="105.315" y="27.336" z="0.0"/>
  <Item StationNum="Z9870" StationName="昭通" RadarType="CC" x="103.72" y="27.352" z="0.0"/>
  <Item StationNum="Z9871" StationName="昆明" RadarType="CC" x="102.578" y="25.052" z="0.0"/>
  <Item StationNum="Z9453" StationName="牡丹江" RadarType="CC" x="129.6" y="44.591" z="0.0"/>
  <Item StationNum="Z9876" StationName="文山" RadarType="CC" x="104.25" y="23.477" z="0.0"/>
  <Item StationNum="Z9879" StationName="思茅" RadarType="CC" x="101.02" y="22.825" z="0.0"/>
  <Item StationNum="Z9454" StationName="佳木斯" RadarType="CC" x="130.318" y="46.796" z="0.0"/>
  <Item StationNum="Z9888" StationName="丽江" RadarType="CC" x="130.318" y="46.796" z="0.0"/>
  <Item StationNum="Z9470" StationName="海拉尔" RadarType="CD" x="119.753" y="49.204" z="0.0"/>
  <Item StationNum="Z9471" StationName="呼和浩特" RadarType="CD" x="111.7" y="40.982" z="0.0"/>
  <Item StationNum="Z9475" StationName="通辽" RadarType="CB" x="122.26" y="43.62" z="0.0"/>
  <Item StationNum="Z9476" StationName="赤峰" RadarType="CD" x="118.966" y="42.233" z="0.0"/>
  <Item StationNum="Z9477" StationName="鄂尔多斯" RadarType="CB" x="110.041" y="39.814" z="0.0"/>
  <Item StationNum="Z9891" StationName="拉萨" RadarType="CD" x="91.134" y="29.66" z="0.0"/>
  <Item StationNum="Z9898" StationName="海口" RadarType="SA" x="110.246" y="19.996" z="0.0"/>
  <Item StationNum="Z9911" StationName="延安" RadarType="CB" x="109.488" y="36.609" z="0.0"/>
  <Item StationNum="Z9912" StationName="榆林" RadarType="CB" x="109.776" y="38.277" z="0.0"/>
  <Item StationNum="Z9513" StationName="南通" RadarType="SA" x="120.962" y="32.079" z="0.0"/>
  <Item StationNum="Z9915" StationName="安康" RadarType="CB" x="109.046" y="32.694" z="0.0"/>
  <Item StationNum="Z9515" StationName="盐城" RadarType="SA" x="120.198" y="33.429" z="0.0"/>
  <Item StationNum="Z9916" StationName="汉中" RadarType="CB" x="107.044" y="33.158" z="0.0"/>
  <Item StationNum="Z9931" StationName="兰州" RadarType="CC" x="103.852" y="36.009" z="0.0"/>
  <Item StationNum="Z9936" StationName="张掖" RadarType="CC" x="100.277" y="39.088" z="0.0"/>
  <Item StationNum="Z9938" StationName="天水" RadarType="CD" x="105.698" y="34.594" z="0.0"/>
  <Item StationNum="Z9951" StationName="银川" RadarType="CD" x="106.215" y="38.479" z="0.0"/>
  <Item StationNum="Z9516" StationName="徐州" RadarType="SA" x="117.152" y="34.293" z="0.0"/>
  <Item StationNum="Z9954" StationName="固原" RadarType="CD" x="106.203" y="35.669" z="0.0"/>
  <Item StationNum="Z9518" StationName="连云港" RadarType="SA" x="119.296" y="34.65" z="0.0"/>
  <Item StationNum="Z9971" StationName="西宁" RadarType="CD" x="101.778" y="36.6" z="0.0"/>
  <Item StationNum="Z9990" StationName="克拉玛依" RadarType="CC" x="84.964" y="45.47" z="0.0"/>
  <Item StationNum="Z9532" StationName="青岛" RadarType="SA" x="120.23" y="35.989" z="0.0"/>
  <Item StationNum="Z9991" StationName="乌鲁木齐" RadarType="CC" x="87.393" y="43.916" z="0.0"/>
  <Item StationNum="Z9535" StationName="烟台" RadarType="SA" x="121.389" y="37.499" z="0.0"/>
  <Item StationNum="Z9993" StationName="石河子" RadarType="CC" x="85.975" y="44.287" z="0.0"/>
  <Item StationNum="Z9539" StationName="临沂" RadarType="SC" x="118.349" y="35.051" z="0.0"/>
  <Item StationNum="Z9996" StationName="库尔勒" RadarType="CC" x="86.203" y="41.76" z="0.0"/>
  <Item StationNum="Z9543" StationName="滨州" RadarType="SC" x="118.001" y="37.367" z="0.0"/>
  <Item StationNum="Z9997" StationName="阿克苏" RadarType="CC" x="80.235" y="41.163" z="0.0"/>
  <Item StationNum="Z9551" StationName="合肥" RadarType="SA" x="117.24" y="31.866" z="0.0"/>
  <Item StationNum="Z9998" StationName="喀什" RadarType="CC" x="76.015" y="39.46" z="0.0"/>
  <Item StationNum="Z9571" StationName="杭州" RadarType="SA" x="120.337" y="30.273" z="0.0"/>
  <Item StationNum="Z9574" StationName="宁波" RadarType="SA" x="121.509" y="30.07" z="0.0"/>
  <Item StationNum="Z9577" StationName="温州" RadarType="SA" x="120.746" y="27.896" z="0.0"/>
  <Item StationNum="Z9579" StationName="金华" RadarType="SB" x="119.645" y="29.218" z="0.0"/>
  <Item StationNum="Z9999" StationName="伊宁" RadarType="CC" x="81.325" y="43.942" z="0.0"/>
  <Item StationNum="Z9591" StationName="福州" RadarType="SA" x="119.54" y="25.992" z="0.0"/>
  <Item StationNum="Z9592" StationName="厦门" RadarType="SA" x="118.081" y="24.487" z="0.0"/>
  <Item StationNum="Z9894" StationName="林芝" RadarType="CD" x="94.396" y="29.633" z="0.0"/>
  <Item StationNum="Z9597" StationName="龙岩" RadarType="SA" x="117.233" y="25.064" z="0.0"/>
  <Item StationNum="Z9599" StationName="建阳" RadarType="SA" x="118.102" y="27.349" z="0.0"/>
  <Item StationNum="Z9852" StationName="遵义" RadarType="CD" x="106.913" y="27.683" z="0.0"/>
  <Item StationNum="Z9854" StationName="都匀" RadarType="CD" x="107.515" y="26.323" z="0.0"/>
  <Item StationNum="Z9662" StationName="阳江" RadarType="SA" x="111.979" y="21.846" z="0.0"/>
  <Item StationNum="Z9716" StationName="荆州" RadarType="SA" x="112.193" y="30.327" z="0.0"/>
  <Item StationNum="Z9718" StationName="恩施" RadarType="SB" x="109.257" y="30.287" z="0.0"/>
  <Item StationNum="Z9717" StationName="宜昌" RadarType="SA" x="111.297" y="30.702" z="0.0"/>
  <Item StationNum="Z9250" StationName="南京" RadarType="SA" x="118.698" y="32.191" z="0.0"/>
  <Item StationNum="Z9859" StationName="兴义" RadarType="CD" x="104.896" y="25.091" z="0.0"/>
  <Item StationNum="Z9531" StationName="济南" RadarType="SA" x="116.781" y="36.803" z="0.0"/>
  <Item StationNum="Z9558" StationName="阜阳" RadarType="SA" x="115.749" y="32.88" z="0.0"/>
  <Item StationNum="Z9538" StationName="泰安" RadarType="CD" x="117.106" y="36.256" z="0.0"/>
  <Item StationNum="Z9313" StationName="张北" RadarType="CB" x="114.7" y="41.15" z="0.0"/>
  <Item StationNum="Z9457" StationName="加格达奇" RadarType="CC" x="124.118" y="50.408" z="0.0"/>
  <Item StationNum="Z9552" StationName="蚌埠" RadarType="SA" x="117.434" y="32.901" z="0.0"/>
  <Item StationNum="Z9555" StationName="马鞍山" RadarType="CC" x="118.516" y="31.701" z="0.0"/>
  <Item StationNum="Z9692" StationName="德宏" RadarType="CC" x="98.394" y="24.489" z="0.0"/>
  <Item StationNum="Z9580" StationName="舟山" RadarType="SB" x="122.109" y="30.069" z="0.0"/>
  <Item StationNum="Z9335" StationName="秦皇岛" RadarType="SA" x="118.881" y="39.881" z="0.0"/>
  <Item StationNum="Z9559" StationName="黄山" RadarType="SA" x="118.158" y="30.133" z="0.0"/>
  <Item StationNum="Z9731" StationName="长沙" RadarType="SA" x="113.012" y="28.46" z="0.0"/>
  <Item StationNum="Z9759" StationName="湛江" RadarType="SA" x="110.525" y="21.012" z="0.0"/>
  <Item StationNum="Z9771" StationName="南宁" RadarType="SA" x="108.4" y="22.81" z="0.0"/>
  <Item StationNum="Z9776" StationName="百色" RadarType="SB" x="106.604" y="23.898" z="0.0"/>
  <Item StationNum="Z9892" StationName="日喀则" RadarType="CD" x="88.891" y="29.247" z="0.0"/>
  <Item StationNum="Z9917" StationName="宝鸡" RadarType="CB" x="107.233" y="34.533" z="0.0"/>
  <Item StationNum="Z9934" StationName="西峰" RadarType="CD" x="107.617" y="35.7" z="0.0"/>
  <Item StationNum="Z9452" StationName="齐齐哈尔" RadarType="CC" x="123.934" y="47.367" z="0.0"/>
  <Item StationNum="Z9593" StationName="宁德" RadarType="CCJ" x="119.678" y="26.564" z="0.0"/>
  <Item StationNum="Z9937" StationName="酒泉" RadarType="CC" x="98.298" y="39.764" z="0.0"/>
  <Item StationNum="Z9762" StationName="河源" RadarType="SA" x="114.607" y="23.69" z="0.0"/>
  <Item StationNum="Z9660" StationName="汕尾" RadarType="SA" x="115.356" y="22.818" z="0.0"/>
  <Item StationNum="Z9779" StationName="北海" RadarType="SB" x="109.042" y="21.447" z="0.0"/>
  <Item StationNum="Z9778" StationName="河池" RadarType="SB" x="107.508" y="24.989" z="0.0"/>
  <Item StationNum="Z9774" StationName="梧州" RadarType="SB" x="111.304" y="23.47" z="0.0"/>
  <Item StationNum="Z9070" StationName="三亚" RadarType="SC" x="109.497" y="18.228" z="0.0"/>
  <Item StationNum="Z9071" StationName="西沙" RadarType="SC" x="112.333" y="16.834" z="0.0"/>
  <Item StationNum="Z9556" StationName="安庆" RadarType="SA" x="116.474" y="30.617" z="0.0"/>
  <Item StationNum="Z9317" StationName="沧州" RadarType="SA" x="116.806" y="38.306" z="0.0"/>
  <Item StationNum="Z9379" StationName="洛阳" RadarType="SB" x="112.452" y="34.643" z="0.0"/>
  <Item StationNum="Z9085" StationName="建三江" RadarType="CC" x="132.625" y="47.233" z="0.0"/>
  <Item StationNum="Z9084" StationName="九三分局" RadarType="CC" x="125.292" y="48.868" z="0.0"/>
  <Item StationNum="Z9085" StationName="伊春" RadarType="CC" x="128.914" y="47.701" z="0.0"/>
  <Item StationNum="Z9722" StationName="随州" RadarType="SB" x="113.389" y="31.726" z="0.0"/>
  <Item StationNum="Z9747" StationName="黄岩" RadarType="CB" x="110.054" y="27.47" z="0.0"/>
  <Item StationNum="Z9739" StationName="邵阳" RadarType="SA" x="111.447" y="27.207" z="0.0"/>
  <Item StationNum="Z9748" StationName="石门" RadarType="SA" x="110.005" y="27.629" z="0.0"/>
  <Item StationNum="Z9730" StationName="岳阳" RadarType="SA" x="113.103" y="29.299" z="0.0"/>
  <Item StationNum="Z9439" StationName="白山" RadarType="CC" x="126.199" y="41.969" z="0.0"/>
  <Item StationNum="Z9433" StationName="延吉" RadarType="CC" x="129.46" y="42.839" z="0.0"/>
  <Item StationNum="Z9519" StationName="常州" RadarType="SA" x="119.78" y="31.901" z="0.0"/>
  <Item StationNum="Z9793" StationName="上饶" RadarType="SA" x="117.977" y="28.443" z="0.0"/>
  <Item StationNum="Z9415" StationName="丹东" RadarType="SC" x="124.157" y="39.876" z="0.0"/>
  <Item StationNum="Z9478" StationName="临河" RadarType="CD" x="107.369" y="40.735" z="0.0"/>
  <Item StationNum="Z9970" StationName="海北" RadarType="CD" x="100.905" y="36.952" z="0.0"/>
  <Item StationNum="Z9355" StationName="长治" RadarType="CC" x="113.055" y="36.224" z="0.0"/>
  <Item StationNum="Z9210" StationName="南汇" RadarType="SA" x="121.885" y="31" z="0.0"/>
  <Item StationNum="Z9818" StationName="达州" RadarType="SC" x="107.53" y="31.17" z="0.0"/>
  <Item StationNum="Z9896" StationName="那曲" RadarType="CD" x="92.061" y="31.481" z="0.0"/>
  <Item StationNum="Z9992" StationName="奎屯" RadarType="CC" x="84.102" y="44.382" z="0.0"/>
  <Item StationNum="Z9080" StationName="塔斯尔海" RadarType="CC" x="82.35" y="44.827" z="0.0"/>
  <Item StationNum="Z9082" StationName="图木舒克" RadarType="CC" x="79.084" y="39.87" z="0.0"/>
  <Item StationNum="Z9081" StationName="五家渠" RadarType="CC" x="87.555" y="44.148" z="0.0"/>
  <Item StationNum="Z9570" StationName="衢州" RadarType="SB" x="118.702" y="29.086" z="0.0"/>
  <Item StationNum="Z9018" StationName="测试" RadarType="CD" x="112.876" y="44.048" z="0.0"/>
  <Item StationNum="Z9091" StationName="黔江" RadarType="CD" x="108.728" y="29.592" z="0.0"/>
  <Item StationNum="Z9090" StationName="万州" RadarType="SB" x="108.683" y="30.803" z="0.0"/>
</Radar>